gut.py
test_gut-1.0.1.dist-info/METADATA
test_gut-1.0.1.dist-info/WHEEL
test_gut-1.0.1.dist-info/entry_points.txt
test_gut-1.0.1.dist-info/top_level.txt
test_gut-1.0.1.dist-info/RECORD
