Metadata-Version: 2.1
Name: test-gut
Version: 1.0.1
Requires-Dist: Click
